oarepo_multilingual/__init__.py
oarepo_multilingual/config.py
oarepo_multilingual/ext.py
oarepo_multilingual/rest.py
oarepo_multilingual/version.py
oarepo_multilingual/datamodels/__init__.py
oarepo_multilingual/datamodels/multilingual-v2.0.0.json5
oarepo_multilingual/jsonschemas/__init__.py
oarepo_multilingual/jsonschemas/multilingual-v2.0.0.json
oarepo_multilingual/mapping/__init__.py
oarepo_multilingual/mapping/mapping_handler.py
oarepo_multilingual/mapping/multilingual_analysis.py
oarepo_multilingual/marshmallow/__init__.py
oarepo_multilingual-2.7.0.dist-info/LICENSE
oarepo_multilingual-2.7.0.dist-info/METADATA
oarepo_multilingual-2.7.0.dist-info/WHEEL
oarepo_multilingual-2.7.0.dist-info/entry_points.txt
oarepo_multilingual-2.7.0.dist-info/top_level.txt
oarepo_multilingual-2.7.0.dist-info/RECORD
