Metadata-Version: 2.1
Name: oarepo-multilingual
Version: 2.7.0
Summary: Multilingual support for OARepo
Home-page: https://github.com/oarepo/oarepo-multilingual
Author: Alzbeta Pokorna
Author-email: alzbeta.pokorna@cesnet.cz
License: MIT
Platform: any
Classifier: Environment :: Web Environment
Classifier: Intended Audience :: Developers
Classifier: License :: OSI Approved :: MIT License
Classifier: Operating System :: OS Independent
Classifier: Programming Language :: Python
Classifier: Topic :: Internet :: WWW/HTTP :: Dynamic Content
Classifier: Topic :: Software Development :: Libraries :: Python Modules
Classifier: Programming Language :: Python :: 2
Classifier: Programming Language :: Python :: 2.7
Classifier: Programming Language :: Python :: 3
Classifier: Programming Language :: Python :: 3.5
Classifier: Development Status :: 4 - Beta
License-File: LICENSE
Requires-Dist: pycountry
Requires-Dist: jsonschema (<4.0.0,>=3.0.0)
Provides-Extra: build
Requires-Dist: oarepo-model-builder ; extra == 'build'
Provides-Extra: tests
Requires-Dist: oarepo-mapping-includes ; extra == 'tests'
Requires-Dist: oarepo[tests] ; extra == 'tests'
